{
    "wallpaper": "/home/soliprem/.config/wpg/wallpapers/00019.png",
    "alpha": "100",

    "special": {
        "background": "#1c1d1e",
        "foreground": "#ffffff",
        "cursor": "#ffffff"
    },
    "colors": {
        "color0": "#1c1d1e",
        "color1": "#775f5a",
        "color2": "#626e7c",
        "color3": "#bca9a5",
        "color4": "#5a6470",
        "color5": "#89898f",
        "color6": "#896e64",
        "color7": "#c6c6c6",
        "color8": "#343637",
        "color9": "#a87267",
        "color10": "#718daf",
        "color11": "#ffccbf",
        "color12": "#67809e",
        "color13": "#9f9fcc",
        "color14": "#c18772",
        "color15": "#ffffff"
    }
}
